[
    {
        "army_name": "Lagertha/Sigrid",
        "unit_type": "infantry",
        "tier": 7,
        "count": 300000,
        "is_rally": false,
        "atk_mod": 3.0,
        "def_mod": 3.0,
        "hp_mod": 1.25,
        "unrevivable_ratio": 0.65,
        "use_dynamic_unrevivable_ratio": true,
        "heroes": [
            {
                "hero_name_or_preset": "Lagertha",
                "talent_ids": [
                    "talent_shieldaxe_attack",
                    "talent_chiefs_might",
                    "talent_fatal_strike"
                ],
                "base_skill_ids": [
                    "base_skill_shield_breaker",
                    "rage_skill_showdown"
                ],
                "plugin_skill_ids": []
            },
            {
                "hero_name_or_preset": "Sigrid",
                "talent_ids": [
                    "talent_northern_blood_feast",
                    "talent_cold_iron_oath",
                    "talent_royal_authority"
                ],
                "base_skill_ids": [
                    "base_skill_winters_coronation",
                    "rage_skill_triumphant_presence"
                ],
                "plugin_skill_ids": []
            }
        ]
    },
    {
        "army_name": "Lagertha/Greta",
        "unit_type": "infantry",
        "tier": 7,
        "count": 300000,
        "is_rally": false,
        "atk_mod": 3.0,
        "def_mod": 3.0,
        "hp_mod": 1.25,
        "unrevivable_ratio": 0.65,
        "use_dynamic_unrevivable_ratio": true,
        "heroes": [
            {
                "hero_name_or_preset": "Lagertha",
                "talent_ids": [
                    "talent_shieldaxe_attack",
                    "talent_chiefs_might",
                    "talent_fatal_strike"
                ],
                "base_skill_ids": [
                    "base_skill_shield_breaker",
                    "rage_skill_showdown"
                ],
                "plugin_skill_ids": []
            },
            {
                "hero_name_or_preset": "Greta",
                "talent_ids": [
                    "talent_shattered_edge",
                    "talent_oathbreakers_blade",
                    "talent_exiled_bloodblade"
                ],
                "base_skill_ids": [
                    "base_skill_broken_blade_charge",
                    "rage_skill_time_of_severance"
                ],
                "plugin_skill_ids": []
            }
        ]
    }
]